olakai_sdk-0.6.1.dist-info/licenses/LICENSE
olakaisdk/__init__.py
olakaisdk/config.py
olakaisdk/context.py
olakaisdk/core.py
olakaisdk/client/__init__.py
olakaisdk/client/api.py
olakaisdk/client/client.py
olakaisdk/extractors/__init__.py
olakaisdk/extractors/base_extractor.py
olakaisdk/extractors/openai_extractor.py
olakaisdk/instrumentation/__init__.py
olakaisdk/instrumentation/base.py
olakaisdk/instrumentation/openai.py
olakaisdk/monitor/__init__.py
olakaisdk/monitor/decorator.py
olakaisdk/shared/__init__.py
olakaisdk/shared/exceptions.py
olakaisdk/shared/types.py
olakai_sdk-0.6.1.dist-info/METADATA
olakai_sdk-0.6.1.dist-info/WHEEL
olakai_sdk-0.6.1.dist-info/top_level.txt
olakai_sdk-0.6.1.dist-info/RECORD
