Metadata-Version: 2.4
Name: olakai-sdk
Version: 0.6.1
Summary: Auto-instrumentation SDK for monitoring and tracking LLM usage (OpenAI, Anthropic, etc.)
Author-email: Olakai <support@olakai.ai>
License-Expression: MIT
Project-URL: Homepage, https://olakai.ai
Project-URL: Documentation, https://app.olakai.ai/docs/getting-started/getting-started
Project-URL: Repository, https://github.com/ailocalnode/py-sdk
Project-URL: Bug Tracker, https://github.com/ailocalnode/py-sdk/issues
Keywords: monitoring,ai,ml,api,sdk,olakai
Classifier: Development Status :: 3 - Alpha
Classifier: Intended Audience :: Developers
Classifier: Topic :: Software Development :: Libraries :: Python Modules
Classifier: Topic :: System :: Monitoring
Classifier: Programming Language :: Python :: 3
Classifier: Programming Language :: Python :: 3.7
Classifier: Programming Language :: Python :: 3.8
Classifier: Programming Language :: Python :: 3.9
Classifier: Programming Language :: Python :: 3.10
Classifier: Programming Language :: Python :: 3.11
Classifier: Programming Language :: Python :: 3.12
Classifier: Operating System :: OS Independent
Requires-Python: >=3.7
License-File: LICENSE
Requires-Dist: requests>=2.25.0
Requires-Dist: typing-extensions>=3.7.4; python_version < "3.8"
Provides-Extra: dev
Requires-Dist: pytest>=6.0; extra == "dev"
Requires-Dist: pytest-cov>=2.0; extra == "dev"
Requires-Dist: pytest-asyncio>=0.18.0; extra == "dev"
Requires-Dist: black>=22.0; extra == "dev"
Requires-Dist: flake8>=4.0; extra == "dev"
Requires-Dist: mypy>=0.900; extra == "dev"
Requires-Dist: build>=0.7.0; extra == "dev"
Requires-Dist: twine>=3.0.0; extra == "dev"
Requires-Dist: ruff>=0.12.7; extra == "dev"
Requires-Dist: openai>=1.0.0; extra == "dev"
Provides-Extra: openai
Requires-Dist: openai>=1.0.0; extra == "openai"
Dynamic: license-file
